LICENSE
README.md
setup.py
easyunicornpkg/__init__.py
easyunicornpkg/__main__.py
easyunicornpkg/easyunicornpkg.py
easyunicornpkg.egg-info/PKG-INFO
easyunicornpkg.egg-info/SOURCES.txt
easyunicornpkg.egg-info/dependency_links.txt
easyunicornpkg.egg-info/entry_points.txt
easyunicornpkg.egg-info/top_level.txt