Metadata-Version: 2.1
Name: easyunicornpkg
Version: 0.0.dev0
Summary: Python utility to build a unicornpkg package table.
Author: Commandcracker
License: Apache Software License
Project-URL: Source, https://github.com/unicornpkg/easyunicornpkg
Project-URL: Tracker, https://github.com/unicornpkg/easyunicornpkg/issues
Classifier: Development Status :: 2 - Pre-Alpha
Classifier: License :: OSI Approved :: Apache Software License
Classifier: Operating System :: OS Independent
Classifier: Programming Language :: Python :: 3
Classifier: Programming Language :: Python :: 3 :: Only
License-File: LICENSE
